pyeletrica/__init__.py
pyeletrica/core/__init__.py
pyeletrica/core/main.py
pyeletrica-0.0.3.dist-info/LICENSE
pyeletrica-0.0.3.dist-info/METADATA
pyeletrica-0.0.3.dist-info/WHEEL
pyeletrica-0.0.3.dist-info/top_level.txt
pyeletrica-0.0.3.dist-info/RECORD
