Metadata-Version: 2.1
Name: pyeletrica
Version: 0.0.3
Summary: Fundamental tools for electrical engineers.
Author-email: Hugo Everaldo Salvador Bezerra <hugoesb@gmail.com>
License: MIT License
Project-URL: Homepage, https://github.com/hugoesb/pyeletrica
Keywords: engineer,electrical
Classifier: License :: OSI Approved :: MIT License
Classifier: Operating System :: OS Independent
Classifier: Programming Language :: Python :: 3
Requires-Python: >=3.6
License-File: LICENSE
Requires-Dist: matplotlib
Requires-Dist: numpy
Requires-Dist: tomli ; python_version < "3.12"
